sagod/__init__.py
sagod/utils.py
sagod/models/__init__.py
sagod/models/adone.py
sagod/models/alarm.py
sagod/models/anomalous.py
sagod/models/anomalydae.py
sagod/models/comga.py
sagod/models/deepae.py
sagod/models/dominant.py
sagod/models/done.py
sagod/models/gaan.py
sagod/models/ocgnn.py
sagod/models/one.py
sagod/models/radar.py
sagod/models/resgcn.py
sagod/models/sadag.py
sagod-0.0.3.dist-info/METADATA
sagod-0.0.3.dist-info/WHEEL
sagod-0.0.3.dist-info/top_level.txt
sagod-0.0.3.dist-info/RECORD
