Metadata-Version: 2.1
Name: sagod
Version: 0.0.3
Summary: SAGOD : Static Attributed Graph Outlier Detection
Home-page: https://github.com/Kaslanarian/SAGOD
Author: Welt Xing
Author-email: xingcy@smail.nju.edu.cn
Maintainer: Welt Xing
Maintainer-email: xingcy@smail.nju.edu.cn
License: MIT License
Requires-Dist: numpy
Requires-Dist: sklearn
Requires-Dist: pyod
Requires-Dist: torch
Requires-Dist: torch-geometric
